pylamine-0.2.1.dist-info/METADATA
pylamine-0.2.1.dist-info/WHEEL
pylamine/error.py
pylamine/io.py
pylamine/__init__.py
pylamine/type.py
pylamine/utils.py
pylamine/py.typed
pylamine/pylamine.cpython-39-darwin.so
pylamine-0.2.1.dist-info/RECORD
