Metadata-Version: 2.1
Name: pylamine
Version: 0.2.1
Summary: Python bindings for Calamine.
Home-Page: https://github.com/cnpryer/pylamine
Author: Chris <cnpryer@gmail.com>
Author-email: Chris <cnpryer@gmail.com>
License: MIT
Project-URL: Source Code, https://github.com/cnpryer/pylamine.git
